{
	"name": "Sprite",
	"plugin-id": "Sprite",
	"sid": 187577981065754,
	"isGlobal": false,
	"instanceVariables": [],
	"behaviorTypes": [],
	"effectTypes": [
		{
			"effectId": "tint",
			"name": "Tonalidade"
		}
	],
	"animations": {
		"items": [
			{
				"frames": [
					{
						"width": 250,
						"height": 250,
						"originX": 0.5,
						"originY": 0.5,
						"originalSource": "",
						"exportFormat": "lossless",
						"exportQuality": 0.8,
						"imageSpriteId": 2155294,
						"useCollisionPoly": true,
						"duration": 1,
						"tag": ""
					}
				],
				"sid": 266012106872927,
				"name": "Animation 1",
				"isLooping": false,
				"isPingPong": false,
				"repeatCount": 1,
				"repeatTo": 0,
				"speed": 5
			}
		],
		"subfolders": []
	}
}